[
    {
        "tanggal": "2023-07-20",
        "idtransaksi": "6222238",
        "tipetransaksi": "K",
        "sampah": "2",
        "kuantitas": 3.0,
        "nilaisatuan": 300.0,
        "total": 900.0,
        "saldo": 900.0
    },
    {
        "tanggal": "2023-07-20",
        "idtransaksi": "7455471",
        "tipetransaksi": "K",
        "sampah": "4",
        "kuantitas": 1.0,
        "nilaisatuan": 1000.0,
        "total": 1000.0,
        "saldo": 1900.0
    },
    {
        "tanggal": "2023-07-20",
        "idtransaksi": "8348966",
        "tipetransaksi": "D",
        "sampah": 0,
        "kuantitas": 1,
        "nilaisatuan": 1000,
        "total": 1000,
        "saldo": 900.0
    },
    {
        "tanggal": "2023-07-20",
        "idtransaksi": "KK50072",
        "tipetransaksi": "K",
        "sampah": "2",
        "kuantitas": 100.0,
        "nilaisatuan": 300.0,
        "total": 30000.0,
        "saldo": 102900.0
    }
]